{
 "generated_at": "2026-06-12T14:26:16+00:00",
 "totals": {
  "comments": 32593,
  "discussions": 2146,
  "communities": 27,
  "states": [
   "AZ"
  ],
  "first_date": "2026-04-13",
  "last_date": "2026-06-12"
 },
 "daily": [
  {
   "date": "2026-04-13",
   "state": "AZ",
   "comments": 231
  },
  {
   "date": "2026-04-14",
   "state": "AZ",
   "comments": 278
  },
  {
   "date": "2026-04-15",
   "state": "AZ",
   "comments": 376
  },
  {
   "date": "2026-04-16",
   "state": "AZ",
   "comments": 262
  },
  {
   "date": "2026-04-17",
   "state": "AZ",
   "comments": 462
  },
  {
   "date": "2026-04-18",
   "state": "AZ",
   "comments": 319
  },
  {
   "date": "2026-04-19",
   "state": "AZ",
   "comments": 501
  },
  {
   "date": "2026-04-20",
   "state": "AZ",
   "comments": 254
  },
  {
   "date": "2026-04-21",
   "state": "AZ",
   "comments": 244
  },
  {
   "date": "2026-04-22",
   "state": "AZ",
   "comments": 376
  },
  {
   "date": "2026-04-23",
   "state": "AZ",
   "comments": 412
  },
  {
   "date": "2026-04-24",
   "state": "AZ",
   "comments": 433
  },
  {
   "date": "2026-04-25",
   "state": "AZ",
   "comments": 243
  },
  {
   "date": "2026-04-26",
   "state": "AZ",
   "comments": 226
  },
  {
   "date": "2026-04-27",
   "state": "AZ",
   "comments": 292
  },
  {
   "date": "2026-04-28",
   "state": "AZ",
   "comments": 348
  },
  {
   "date": "2026-04-29",
   "state": "AZ",
   "comments": 331
  },
  {
   "date": "2026-04-30",
   "state": "AZ",
   "comments": 476
  },
  {
   "date": "2026-05-01",
   "state": "AZ",
   "comments": 424
  },
  {
   "date": "2026-05-02",
   "state": "AZ",
   "comments": 268
  },
  {
   "date": "2026-05-03",
   "state": "AZ",
   "comments": 295
  },
  {
   "date": "2026-05-04",
   "state": "AZ",
   "comments": 502
  },
  {
   "date": "2026-05-05",
   "state": "AZ",
   "comments": 282
  },
  {
   "date": "2026-05-06",
   "state": "AZ",
   "comments": 332
  },
  {
   "date": "2026-05-07",
   "state": "AZ",
   "comments": 673
  },
  {
   "date": "2026-05-08",
   "state": "AZ",
   "comments": 579
  },
  {
   "date": "2026-05-09",
   "state": "AZ",
   "comments": 271
  },
  {
   "date": "2026-05-10",
   "state": "AZ",
   "comments": 385
  },
  {
   "date": "2026-05-11",
   "state": "AZ",
   "comments": 322
  },
  {
   "date": "2026-05-12",
   "state": "AZ",
   "comments": 358
  },
  {
   "date": "2026-05-13",
   "state": "AZ",
   "comments": 511
  },
  {
   "date": "2026-05-14",
   "state": "AZ",
   "comments": 556
  },
  {
   "date": "2026-05-15",
   "state": "AZ",
   "comments": 539
  },
  {
   "date": "2026-05-16",
   "state": "AZ",
   "comments": 352
  },
  {
   "date": "2026-05-17",
   "state": "AZ",
   "comments": 338
  },
  {
   "date": "2026-05-18",
   "state": "AZ",
   "comments": 383
  },
  {
   "date": "2026-05-19",
   "state": "AZ",
   "comments": 411
  },
  {
   "date": "2026-05-20",
   "state": "AZ",
   "comments": 567
  },
  {
   "date": "2026-05-21",
   "state": "AZ",
   "comments": 432
  },
  {
   "date": "2026-05-22",
   "state": "AZ",
   "comments": 369
  },
  {
   "date": "2026-05-23",
   "state": "AZ",
   "comments": 319
  },
  {
   "date": "2026-05-24",
   "state": "AZ",
   "comments": 331
  },
  {
   "date": "2026-05-25",
   "state": "AZ",
   "comments": 499
  },
  {
   "date": "2026-05-26",
   "state": "AZ",
   "comments": 652
  },
  {
   "date": "2026-05-27",
   "state": "AZ",
   "comments": 506
  },
  {
   "date": "2026-05-28",
   "state": "AZ",
   "comments": 300
  },
  {
   "date": "2026-05-29",
   "state": "AZ",
   "comments": 459
  },
  {
   "date": "2026-05-30",
   "state": "AZ",
   "comments": 876
  },
  {
   "date": "2026-05-31",
   "state": "AZ",
   "comments": 441
  },
  {
   "date": "2026-06-01",
   "state": "AZ",
   "comments": 500
  },
  {
   "date": "2026-06-02",
   "state": "AZ",
   "comments": 339
  },
  {
   "date": "2026-06-03",
   "state": "AZ",
   "comments": 360
  },
  {
   "date": "2026-06-04",
   "state": "AZ",
   "comments": 383
  },
  {
   "date": "2026-06-05",
   "state": "AZ",
   "comments": 1356
  },
  {
   "date": "2026-06-06",
   "state": "AZ",
   "comments": 1024
  },
  {
   "date": "2026-06-07",
   "state": "AZ",
   "comments": 1220
  },
  {
   "date": "2026-06-08",
   "state": "AZ",
   "comments": 1459
  },
  {
   "date": "2026-06-09",
   "state": "AZ",
   "comments": 1541
  },
  {
   "date": "2026-06-10",
   "state": "AZ",
   "comments": 2314
  },
  {
   "date": "2026-06-11",
   "state": "AZ",
   "comments": 2234
  },
  {
   "date": "2026-06-12",
   "state": "AZ",
   "comments": 267
  }
 ],
 "heat": [
  {
   "lat": 33.644893,
   "lon": -112.395034,
   "date": "2026-04-13",
   "weight": 10.0
  },
  {
   "lat": 33.433545,
   "lon": -111.8504,
   "date": "2026-04-13",
   "weight": 22.0
  },
  {
   "lat": 33.317828,
   "lon": -111.830541,
   "date": "2026-04-13",
   "weight": 17.0
  },
  {
   "lat": 33.419233,
   "lon": -112.326866,
   "date": "2026-04-13",
   "weight": 2.0
  },
  {
   "lat": 34.878547,
   "lon": -111.858031,
   "date": "2026-04-13",
   "weight": 14.0
  },
  {
   "lat": 33.192391,
   "lon": -111.66594,
   "date": "2026-04-13",
   "weight": 5.0
  },
  {
   "lat": 35.189512,
   "lon": -111.654712,
   "date": "2026-04-13",
   "weight": 27.0
  },
  {
   "lat": 33.42744,
   "lon": -111.934004,
   "date": "2026-04-13",
   "weight": 10.0
  },
  {
   "lat": 33.317828,
   "lon": -111.830541,
   "date": "2026-04-14",
   "weight": 28.0
  },
  {
   "lat": 33.419233,
   "lon": -112.326866,
   "date": "2026-04-14",
   "weight": 1.0
  },
  {
   "lat": 32.217037,
   "lon": -110.971338,
   "date": "2026-04-14",
   "weight": 3.0
  },
  {
   "lat": 34.878547,
   "lon": -111.858031,
   "date": "2026-04-14",
   "weight": 18.0
  },
  {
   "lat": 33.644893,
   "lon": -112.395034,
   "date": "2026-04-14",
   "weight": 16.0
  },
  {
   "lat": 33.433545,
   "lon": -111.8504,
   "date": "2026-04-14",
   "weight": 62.0
  },
  {
   "lat": 33.42744,
   "lon": -111.934004,
   "date": "2026-04-14",
   "weight": 55.0
  },
  {
   "lat": 35.189512,
   "lon": -111.654712,
   "date": "2026-04-14",
   "weight": 22.0
  },
  {
   "lat": 32.231069,
   "lon": -110.949568,
   "date": "2026-04-14",
   "weight": 2.0
  },
  {
   "lat": 33.192391,
   "lon": -111.66594,
   "date": "2026-04-14",
   "weight": 2.0
  },
  {
   "lat": 33.192391,
   "lon": -111.66594,
   "date": "2026-04-15",
   "weight": 4.0
  },
  {
   "lat": 35.189512,
   "lon": -111.654712,
   "date": "2026-04-15",
   "weight": 26.0
  },
  {
   "lat": 32.231069,
   "lon": -110.949568,
   "date": "2026-04-15",
   "weight": 30.0
  },
  {
   "lat": 33.352445,
   "lon": -111.812562,
   "date": "2026-04-15",
   "weight": 8.0
  },
  {
   "lat": 33.42744,
   "lon": -111.934004,
   "date": "2026-04-15",
   "weight": 44.0
  },
  {
   "lat": 33.317828,
   "lon": -111.830541,
   "date": "2026-04-15",
   "weight": 40.0
  },
  {
   "lat": 33.419233,
   "lon": -112.326866,
   "date": "2026-04-15",
   "weight": 2.0
  },
  {
   "lat": 32.217037,
   "lon": -110.971338,
   "date": "2026-04-15",
   "weight": 3.0
  },
  {
   "lat": 34.878547,
   "lon": -111.858031,
   "date": "2026-04-15",
   "weight": 45.0
  },
  {
   "lat": 33.644893,
   "lon": -112.395034,
   "date": "2026-04-15",
   "weight": 10.0
  },
  {
   "lat": 33.433545,
   "lon": -111.8504,
   "date": "2026-04-15",
   "weight": 28.0
  },
  {
   "lat": 33.317828,
   "lon": -111.830541,
   "date": "2026-04-16",
   "weight": 20.0
  },
  {
   "lat": 32.217037,
   "lon": -110.971338,
   "date": "2026-04-16",
   "weight": 6.0
  },
  {
   "lat": 34.878547,
   "lon": -111.858031,
   "date": "2026-04-16",
   "weight": 21.0
  },
  {
   "lat": 33.433545,
   "lon": -111.8504,
   "date": "2026-04-16",
   "weight": 18.0
  },
  {
   "lat": 33.42744,
   "lon": -111.934004,
   "date": "2026-04-16",
   "weight": 51.0
  },
  {
   "lat": 35.189512,
   "lon": -111.654712,
   "date": "2026-04-16",
   "weight": 16.0
  },
  {
   "lat": 32.231069,
   "lon": -110.949568,
   "date": "2026-04-16",
   "weight": 18.0
  },
  {
   "lat": 33.352445,
   "lon": -111.812562,
   "date": "2026-04-16",
   "weight": 15.0
  },
  {
   "lat": 33.192391,
   "lon": -111.66594,
   "date": "2026-04-16",
   "weight": 22.0
  },
  {
   "lat": 32.217037,
   "lon": -110.971338,
   "date": "2026-04-17",
   "weight": 2.0
  },
  {
   "lat": 34.878547,
   "lon": -111.858031,
   "date": "2026-04-17",
   "weight": 73.0
  },
  {
   "lat": 33.644893,
   "lon": -112.395034,
   "date": "2026-04-17",
   "weight": 1.0
  },
  {
   "lat": 33.433545,
   "lon": -111.8504,
   "date": "2026-04-17",
   "weight": 14.0
  },
  {
   "lat": 33.317828,
   "lon": -111.830541,
   "date": "2026-04-17",
   "weight": 14.0
  },
  {
   "lat": 33.42744,
   "lon": -111.934004,
   "date": "2026-04-17",
   "weight": 34.0
  },
  {
   "lat": 33.352445,
   "lon": -111.812562,
   "date": "2026-04-17",
   "weight": 6.0
  },
  {
   "lat": 35.189512,
   "lon": -111.654712,
   "date": "2026-04-17",
   "weight": 19.0
  },
  {
   "lat": 32.231069,
   "lon": -110.949568,
   "date": "2026-04-17",
   "weight": 28.0
  },
  {
   "lat": 33.192391,
   "lon": -111.66594,
   "date": "2026-04-17",
   "weight": 12.0
  },
  {
   "lat": 33.248065,
   "lon": -111.489238,
   "date": "2026-04-17",
   "weight": 3.0
  },
  {
   "lat": 32.217037,
   "lon": -110.971338,
   "date": "2026-04-18",
   "weight": 1.0
  },
  {
   "lat": 34.878547,
   "lon": -111.858031,
   "date": "2026-04-18",
   "weight": 21.0
  },
  {
   "lat": 33.317828,
   "lon": -111.830541,
   "date": "2026-04-18",
   "weight": 17.0
  },
  {
   "lat": 33.433545,
   "lon": -111.8504,
   "date": "2026-04-18",
   "weight": 12.0
  },
  {
   "lat": 33.192391,
   "lon": -111.66594,
   "date": "2026-04-18",
   "weight": 2.0
  },
  {
   "lat": 33.42744,
   "lon": -111.934004,
   "date": "2026-04-18",
   "weight": 18.0
  },
  {
   "lat": 33.248065,
   "lon": -111.489238,
   "date": "2026-04-18",
   "weight": 3.0
  },
  {
   "lat": 33.352445,
   "lon": -111.812562,
   "date": "2026-04-18",
   "weight": 1.0
  },
  {
   "lat": 35.189512,
   "lon": -111.654712,
   "date": "2026-04-18",
   "weight": 3.0
  },
  {
   "lat": 32.231069,
   "lon": -110.949568,
   "date": "2026-04-18",
   "weight": 20.0
  },
  {
   "lat": 33.192391,
   "lon": -111.66594,
   "date": "2026-04-19",
   "weight": 1.0
  },
  {
   "lat": 33.352445,
   "lon": -111.812562,
   "date": "2026-04-19",
   "weight": 145.0
  },
  {
   "lat": 35.189512,
   "lon": -111.654712,
   "date": "2026-04-19",
   "weight": 12.0
  },
  {
   "lat": 32.231069,
   "lon": -110.949568,
   "date": "2026-04-19",
   "weight": 14.0
  },
  {
   "lat": 33.248065,
   "lon": -111.489238,
   "date": "2026-04-19",
   "weight": 5.0
  },
  {
   "lat": 33.42744,
   "lon": -111.934004,
   "date": "2026-04-19",
   "weight": 13.0
  },
  {
   "lat": 33.644893,
   "lon": -112.395034,
   "date": "2026-04-19",
   "weight": 2.0
  },
  {
   "lat": 33.433545,
   "lon": -111.8504,
   "date": "2026-04-19",
   "weight": 13.0
  },
  {
   "lat": 33.317828,
   "lon": -111.830541,
   "date": "2026-04-19",
   "weight": 46.0
  },
  {
   "lat": 32.923874,
   "lon": -112.206708,
   "date": "2026-04-19",
   "weight": 2.0
  },
  {
   "lat": 32.217037,
   "lon": -110.971338,
   "date": "2026-04-19",
   "weight": 2.0
  },
  {
   "lat": 34.878547,
   "lon": -111.858031,
   "date": "2026-04-19",
   "weight": 16.0
  },
  {
   "lat": 33.192391,
   "lon": -111.66594,
   "date": "2026-04-20",
   "weight": 4.0
  },
  {
   "lat": 35.189512,
   "lon": -111.654712,
   "date": "2026-04-20",
   "weight": 16.0
  },
  {
   "lat": 32.231069,
   "lon": -110.949568,
   "date": "2026-04-20",
   "weight": 16.0
  },
  {
   "lat": 33.352445,
   "lon": -111.812562,
   "date": "2026-04-20",
   "weight": 20.0
  },
  {
   "lat": 33.42744,
   "lon": -111.934004,
   "date": "2026-04-20",
   "weight": 20.0
  },
  {
   "lat": 33.317828,
   "lon": -111.830541,
   "date": "2026-04-20",
   "weight": 5.0
  },
  {
   "lat": 32.217037,
   "lon": -110.971338,
   "date": "2026-04-20",
   "weight": 5.0
  },
  {
   "lat": 34.878547,
   "lon": -111.858031,
   "date": "2026-04-20",
   "weight": 8.0
  },
  {
   "lat": 33.644893,
   "lon": -112.395034,
   "date": "2026-04-20",
   "weight": 6.0
  },
  {
   "lat": 33.433545,
   "lon": -111.8504,
   "date": "2026-04-20",
   "weight": 32.0
  },
  {
   "lat": 33.644893,
   "lon": -112.395034,
   "date": "2026-04-21",
   "weight": 1.0
  },
  {
   "lat": 33.433545,
   "lon": -111.8504,
   "date": "2026-04-21",
   "weight": 54.0
  },
  {
   "lat": 33.317828,
   "lon": -111.830541,
   "date": "2026-04-21",
   "weight": 26.0
  },
  {
   "lat": 32.217037,
   "lon": -110.971338,
   "date": "2026-04-21",
   "weight": 3.0
  },
  {
   "lat": 34.878547,
   "lon": -111.858031,
   "date": "2026-04-21",
   "weight": 6.0
  },
  {
   "lat": 35.189512,
   "lon": -111.654712,
   "date": "2026-04-21",
   "weight": 8.0
  },
  {
   "lat": 32.231069,
   "lon": -110.949568,
   "date": "2026-04-21",
   "weight": 9.0
  },
  {
   "lat": 33.352445,
   "lon": -111.812562,
   "date": "2026-04-21",
   "weight": 35.0
  },
  {
   "lat": 33.42744,
   "lon": -111.934004,
   "date": "2026-04-21",
   "weight": 28.0
  },
  {
   "lat": 33.248065,
   "lon": -111.489238,
   "date": "2026-04-21",
   "weight": 1.0
  },
  {
   "lat": 32.217037,
   "lon": -110.971338,
   "date": "2026-04-22",
   "weight": 3.0
  },
  {
   "lat": 34.878547,
   "lon": -111.858031,
   "date": "2026-04-22",
   "weight": 28.0
  },
  {
   "lat": 33.317828,
   "lon": -111.830541,
   "date": "2026-04-22",
   "weight": 39.0
  },
  {
   "lat": 33.352445,
   "lon": -111.812562,
   "date": "2026-04-22",
   "weight": 19.0
  },
  {
   "lat": 35.189512,
   "lon": -111.654712,
   "date": "2026-04-22",
   "weight": 4.0
  },
  {
   "lat": 32.231069,
   "lon": -110.949568,
   "date": "2026-04-22",
   "weight": 30.0
  },
  {
   "lat": 33.248065,
   "lon": -111.489238,
   "date": "2026-04-22",
   "weight": 1.0
  },
  {
   "lat": 33.433545,
   "lon": -111.8504,
   "date": "2026-04-22",
   "weight": 29.0
  },
  {
   "lat": 33.42744,
   "lon": -111.934004,
   "date": "2026-04-22",
   "weight": 44.0
  },
  {
   "lat": 33.644893,
   "lon": -112.395034,
   "date": "2026-04-23",
   "weight": 33.0
  },
  {
   "lat": 33.433545,
   "lon": -111.8504,
   "date": "2026-04-23",
   "weight": 42.0
  },
  {
   "lat": 32.217037,
   "lon": -110.971338,
   "date": "2026-04-23",
   "weight": 6.0
  },
  {
   "lat": 34.878547,
   "lon": -111.858031,
   "date": "2026-04-23",
   "weight": 35.0
  },
  {
   "lat": 33.192391,
   "lon": -111.66594,
   "date": "2026-04-23",
   "weight": 8.0
  },
  {
   "lat": 35.189512,
   "lon": -111.654712,
   "date": "2026-04-23",
   "weight": 16.0
  },
  {
   "lat": 32.231069,
   "lon": -110.949568,
   "date": "2026-04-23",
   "weight": 12.0
  },
  {
   "lat": 33.317828,
   "lon": -111.830541,
   "date": "2026-04-23",
   "weight": 22.0
  },
  {
   "lat": 33.42744,
   "lon": -111.934004,
   "date": "2026-04-23",
   "weight": 92.0
  },
  {
   "lat": 33.352445,
   "lon": -111.812562,
   "date": "2026-04-23",
   "weight": 18.0
  },
  {
   "lat": 33.192391,
   "lon": -111.66594,
   "date": "2026-04-24",
   "weight": 31.0
  },
  {
   "lat": 35.189512,
   "lon": -111.654712,
   "date": "2026-04-24",
   "weight": 9.0
  },
  {
   "lat": 32.231069,
   "lon": -110.949568,
   "date": "2026-04-24",
   "weight": 3.0
  },
  {
   "lat": 33.352445,
   "lon": -111.812562,
   "date": "2026-04-24",
   "weight": 17.0
  },
  {
   "lat": 33.42744,
   "lon": -111.934004,
   "date": "2026-04-24",
   "weight": 101.0
  },
  {
   "lat": 33.317828,
   "lon": -111.830541,
   "date": "2026-04-24",
   "weight": 36.0
  },
  {
   "lat": 32.217037,
   "lon": -110.971338,
   "date": "2026-04-24",
   "weight": 3.0
  },
  {
   "lat": 34.878547,
   "lon": -111.858031,
   "date": "2026-04-24",
   "weight": 20.0
  },
  {
   "lat": 33.644893,
   "lon": -112.395034,
   "date": "2026-04-24",
   "weight": 28.0
  },
  {
   "lat": 33.433545,
   "lon": -111.8504,
   "date": "2026-04-24",
   "weight": 63.0
  },
  {
   "lat": 33.644893,
   "lon": -112.395034,
   "date": "2026-04-25",
   "weight": 8.0
  },
  {
   "lat": 33.433545,
   "lon": -111.8504,
   "date": "2026-04-25",
   "weight": 50.0
  },
  {
   "lat": 32.217037,
   "lon": -110.971338,
   "date": "2026-04-25",
   "weight": 6.0
  },
  {
   "lat": 34.878547,
   "lon": -111.858031,
   "date": "2026-04-25",
   "weight": 11.0
  },
  {
   "lat": 33.192391,
   "lon": -111.66594,
   "date": "2026-04-25",
   "weight": 7.0
  },
  {
   "lat": 35.189512,
   "lon": -111.654712,
   "date": "2026-04-25",
   "weight": 5.0
  },
  {
   "lat": 32.231069,
   "lon": -110.949568,
   "date": "2026-04-25",
   "weight": 4.0
  },
  {
   "lat": 33.317828,
   "lon": -111.830541,
   "date": "2026-04-25",
   "weight": 34.0
  },
  {
   "lat": 33.42744,
   "lon": -111.934004,
   "date": "2026-04-25",
   "weight": 65.0
  },
  {
   "lat": 33.352445,
   "lon": -111.812562,
   "date": "2026-04-25",
   "weight": 4.0
  },
  {
   "lat": 33.192391,
   "lon": -111.66594,
   "date": "2026-04-26",
   "weight": 6.0
  },
  {
   "lat": 35.189512,
   "lon": -111.654712,
   "date": "2026-04-26",
   "weight": 4.0
  },
  {
   "lat": 32.231069,
   "lon": -110.949568,
   "date": "2026-04-26",
   "weight": 2.0
  },
  {
   "lat": 33.42744,
   "lon": -111.934004,
   "date": "2026-04-26",
   "weight": 48.0
  },
  {
   "lat": 33.317828,
   "lon": -111.830541,
   "date": "2026-04-26",
   "weight": 24.0
  },
  {
   "lat": 32.217037,
   "lon": -110.971338,
   "date": "2026-04-26",
   "weight": 4.0
  },
  {
   "lat": 34.878547,
   "lon": -111.858031,
   "date": "2026-04-26",
   "weight": 35.0
  },
  {
   "lat": 33.644893,
   "lon": -112.395034,
   "date": "2026-04-26",
   "weight": 13.0
  },
  {
   "lat": 33.433545,
   "lon": -111.8504,
   "date": "2026-04-26",
   "weight": 15.0
  },
  {
   "lat": 33.317828,
   "lon": -111.830541,
   "date": "2026-04-27",
   "weight": 12.0
  },
  {
   "lat": 33.644893,
   "lon": -112.395034,
   "date": "2026-04-27",
   "weight": 1.0
  },
  {
   "lat": 33.433545,
   "lon": -111.8504,
   "date": "2026-04-27",
   "weight": 53.0
  },
  {
   "lat": 32.217037,
   "lon": -110.971338,
   "date": "2026-04-27",
   "weight": 3.0
  },
  {
   "lat": 34.878547,
   "lon": -111.858031,
   "date": "2026-04-27",
   "weight": 34.0
  },
  {
   "lat": 33.248065,
   "lon": -111.489238,
   "date": "2026-04-27",
   "weight": 2.0
  },
  {
   "lat": 33.192391,
   "lon": -111.66594,
   "date": "2026-04-27",
   "weight": 10.0
  },
  {
   "lat": 33.352445,
   "lon": -111.812562,
   "date": "2026-04-27",
   "weight": 3.0
  },
  {
   "lat": 33.42744,
   "lon": -111.934004,
   "date": "2026-04-27",
   "weight": 77.0
  },
  {
   "lat": 35.189512,
   "lon": -111.654712,
   "date": "2026-04-27",
   "weight": 3.0
  },
  {
   "lat": 32.231069,
   "lon": -110.949568,
   "date": "2026-04-27",
   "weight": 13.0
  },
  {
   "lat": 33.192391,
   "lon": -111.66594,
   "date": "2026-04-28",
   "weight": 13.0
  },
  {
   "lat": 33.352445,
   "lon": -111.812562,
   "date": "2026-04-28",
   "weight": 6.0
  },
  {
   "lat": 35.189512,
   "lon": -111.654712,
   "date": "2026-04-28",
   "weight": 10.0
  },
  {
   "lat": 32.231069,
   "lon": -110.949568,
   "date": "2026-04-28",
   "weight": 14.0
  },
  {
   "lat": 33.572326,
   "lon": -112.248142,
   "date": "2026-04-28",
   "weight": 8.0
  },
  {
   "lat": 33.42744,
   "lon": -111.934004,
   "date": "2026-04-28",
   "weight": 83.0
  },
  {
   "lat": 33.644893,
   "lon": -112.395034,
   "date": "2026-04-28",
   "weight": 5.0
  },
  {
   "lat": 33.433545,
   "lon": -111.8504,
   "date": "2026-04-28",
   "weight": 58.0
  },
  {
   "lat": 33.317828,
   "lon": -111.830541,
   "date": "2026-04-28",
   "weight": 10.0
  },
  {
   "lat": 32.923874,
   "lon": -112.206708,
   "date": "2026-04-28",
   "weight": 1.0
  },
  {
   "lat": 32.217037,
   "lon": -110.971338,
   "date": "2026-04-28",
   "weight": 1.0
  },
  {
   "lat": 34.878547,
   "lon": -111.858031,
   "date": "2026-04-28",
   "weight": 50.0
  },
  {
   "lat": 33.42744,
   "lon": -111.934004,
   "date": "2026-04-29",
   "weight": 110.0
  },
  {
   "lat": 33.352445,
   "lon": -111.812562,
   "date": "2026-04-29",
   "weight": 5.0
  },
  {
   "lat": 35.189512,
   "lon": -111.654712,
   "date": "2026-04-29",
   "weight": 4.0
  },
  {
   "lat": 32.231069,
   "lon": -110.949568,
   "date": "2026-04-29",
   "weight": 6.0
  },
  {
   "lat": 33.317828,
   "lon": -111.830541,
   "date": "2026-04-29",
   "weight": 15.0
  },
  {
   "lat": 33.572326,
   "lon": -112.248142,
   "date": "2026-04-29",
   "weight": 3.0
  },
  {
   "lat": 33.192391,
   "lon": -111.66594,
   "date": "2026-04-29",
   "weight": 8.0
  },
  {
   "lat": 32.217037,
   "lon": -110.971338,
   "date": "2026-04-29",
   "weight": 16.0
  },
  {
   "lat": 34.878547,
   "lon": -111.858031,
   "date": "2026-04-29",
   "weight": 49.0
  },
  {
   "lat": 33.644893,
   "lon": -112.395034,
   "date": "2026-04-29",
   "weight": 8.0
  },
  {
   "lat": 33.433545,
   "lon": -111.8504,
   "date": "2026-04-29",
   "weight": 26.0
  },
  {
   "lat": 33.42744,
   "lon": -111.934004,
   "date": "2026-04-30",
   "weight": 88.0
  },
  {
   "lat": 33.352445,
   "lon": -111.812562,
   "date": "2026-04-30",
   "weight": 1.0
  },
  {
   "lat": 35.189512,
   "lon": -111.654712,
   "date": "2026-04-30",
   "weight": 8.0
  },
  {
   "lat": 32.231069,
   "lon": -110.949568,
   "date": "2026-04-30",
   "weight": 52.0
  },
  {
   "lat": 32.923874,
   "lon": -112.206708,
   "date": "2026-04-30",
   "weight": 1.0
  },
  {
   "lat": 33.317828,
   "lon": -111.830541,
   "date": "2026-04-30",
   "weight": 12.0
  },
  {
   "lat": 33.192391,
   "lon": -111.66594,
   "date": "2026-04-30",
   "weight": 7.0
  },
  {
   "lat": 32.217037,
   "lon": -110.971338,
   "date": "2026-04-30",
   "weight": 4.0
  },
  {
   "lat": 34.878547,
   "lon": -111.858031,
   "date": "2026-04-30",
   "weight": 50.0
  },
  {
   "lat": 33.644893,
   "lon": -112.395034,
   "date": "2026-04-30",
   "weight": 1.0
  },
  {
   "lat": 33.433545,
   "lon": -111.8504,
   "date": "2026-04-30",
   "weight": 64.0
  },
  {
   "lat": 33.644893,
   "lon": -112.395034,
   "date": "2026-05-01",
   "weight": 16.0
  },
  {
   "lat": 33.433545,
   "lon": -111.8504,
   "date": "2026-05-01",
   "weight": 57.0
  },
  {
   "lat": 33.317828,
   "lon": -111.830541,
   "date": "2026-05-01",
   "weight": 26.0
  },
  {
   "lat": 32.217037,
   "lon": -110.971338,
   "date": "2026-05-01",
   "weight": 11.0
  },
  {
   "lat": 34.878547,
   "lon": -111.858031,
   "date": "2026-05-01",
   "weight": 9.0
  },
  {
   "lat": 35.189512,
   "lon": -111.654712,
   "date": "2026-05-01",
   "weight": 15.0
  },
  {
   "lat": 32.231069,
   "lon": -110.949568,
   "date": "2026-05-01",
   "weight": 29.0
  },
  {
   "lat": 33.352445,
   "lon": -111.812562,
   "date": "2026-05-01",
   "weight": 19.0
  },
  {
   "lat": 33.42744,
   "lon": -111.934004,
   "date": "2026-05-01",
   "weight": 99.0
  },
  {
   "lat": 33.192391,
   "lon": -111.66594,
   "date": "2026-05-01",
   "weight": 6.0
  },
  {
   "lat": 33.644893,
   "lon": -112.395034,
   "date": "2026-05-02",
   "weight": 3.0
  },
  {
   "lat": 33.433545,
   "lon": -111.8504,
   "date": "2026-05-02",
   "weight": 15.0
  },
  {
   "lat": 33.317828,
   "lon": -111.830541,
   "date": "2026-05-02",
   "weight": 11.0
  },
  {
   "lat": 32.217037,
   "lon": -110.971338,
   "date": "2026-05-02",
   "weight": 9.0
  },
  {
   "lat": 34.878547,
   "lon": -111.858031,
   "date": "2026-05-02",
   "weight": 20.0
  },
  {
   "lat": 35.189512,
   "lon": -111.654712,
   "date": "2026-05-02",
   "weight": 8.0
  },
  {
   "lat": 32.231069,
   "lon": -110.949568,
   "date": "2026-05-02",
   "weight": 7.0
  },
  {
   "lat": 33.352445,
   "lon": -111.812562,
   "date": "2026-05-02",
   "weight": 57.0
  },
  {
   "lat": 33.42744,
   "lon": -111.934004,
   "date": "2026-05-02",
   "weight": 70.0
  },
  {
   "lat": 33.192391,
   "lon": -111.66594,
   "date": "2026-05-02",
   "weight": 4.0
  },
  {
   "lat": 33.317828,
   "lon": -111.830541,
   "date": "2026-05-03",
   "weight": 49.0
  },
  {
   "lat": 33.644893,
   "lon": -112.395034,
   "date": "2026-05-03",
   "weight": 6.0
  },
  {
   "lat": 33.433545,
   "lon": -111.8504,
   "date": "2026-05-03",
   "weight": 32.0
  },
  {
   "lat": 34.598251,
   "lon": -112.33074,
   "date": "2026-05-03",
   "weight": 1.0
  },
  {
   "lat": 32.217037,
   "lon": -110.971338,
   "date": "2026-05-03",
   "weight": 5.0
  },
  {
   "lat": 34.878547,
   "lon": -111.858031,
   "date": "2026-05-03",
   "weight": 16.0
  },
  {
   "lat": 33.192391,
   "lon": -111.66594,
   "date": "2026-05-03",
   "weight": 2.0
  },
  {
   "lat": 33.352445,
   "lon": -111.812562,
   "date": "2026-05-03",
   "weight": 9.0
  },
  {
   "lat": 33.42744,
   "lon": -111.934004,
   "date": "2026-05-03",
   "weight": 67.0
  },
  {
   "lat": 35.189512,
   "lon": -111.654712,
   "date": "2026-05-03",
   "weight": 6.0
  },
  {
   "lat": 32.231069,
   "lon": -110.949568,
   "date": "2026-05-03",
   "weight": 8.0
  },
  {
   "lat": 33.644893,
   "lon": -112.395034,
   "date": "2026-05-04",
   "weight": 2.0
  },
  {
   "lat": 33.433545,
   "lon": -111.8504,
   "date": "2026-05-04",
   "weight": 89.0
  },
  {
   "lat": 34.598251,
   "lon": -112.33074,
   "date": "2026-05-04",
   "weight": 1.0
  },
  {
   "lat": 33.317828,
   "lon": -111.830541,
   "date": "2026-05-04",
   "weight": 87.0
  },
  {
   "lat": 32.217037,
   "lon": -110.971338,
   "date": "2026-05-04",
   "weight": 1.0
  },
  {
   "lat": 34.878547,
   "lon": -111.858031,
   "date": "2026-05-04",
   "weight": 25.0
  },
  {
   "lat": 35.189512,
   "lon": -111.654712,
   "date": "2026-05-04",
   "weight": 5.0
  },
  {
   "lat": 32.231069,
   "lon": -110.949568,
   "date": "2026-05-04",
   "weight": 3.0
  },
  {
   "lat": 33.352445,
   "lon": -111.812562,
   "date": "2026-05-04",
   "weight": 8.0
  },
  {
   "lat": 33.42744,
   "lon": -111.934004,
   "date": "2026-05-04",
   "weight": 102.0
  },
  {
   "lat": 33.192391,
   "lon": -111.66594,
   "date": "2026-05-04",
   "weight": 5.0
  },
  {
   "lat": 33.192391,
   "lon": -111.66594,
   "date": "2026-05-05",
   "weight": 7.0
  },
  {
   "lat": 33.352445,
   "lon": -111.812562,
   "date": "2026-05-05",
   "weight": 12.0
  },
  {
   "lat": 35.189512,
   "lon": -111.654712,
   "date": "2026-05-05",
   "weight": 3.0
  },
  {
   "lat": 32.231069,
   "lon": -110.949568,
   "date": "2026-05-05",
   "weight": 2.0
  },
  {
   "lat": 33.42744,
   "lon": -111.934004,
   "date": "2026-05-05",
   "weight": 42.0
  },
  {
   "lat": 33.644893,
   "lon": -112.395034,
   "date": "2026-05-05",
   "weight": 1.0
  },
  {
   "lat": 33.433545,
   "lon": -111.8504,
   "date": "2026-05-05",
   "weight": 60.0
  },
  {
   "lat": 33.317828,
   "lon": -111.830541,
   "date": "2026-05-05",
   "weight": 42.0
  },
  {
   "lat": 32.217037,
   "lon": -110.971338,
   "date": "2026-05-05",
   "weight": 1.0
  },
  {
   "lat": 34.878547,
   "lon": -111.858031,
   "date": "2026-05-05",
   "weight": 36.0
  },
  {
   "lat": 33.317828,
   "lon": -111.830541,
   "date": "2026-05-06",
   "weight": 60.0
  },
  {
   "lat": 34.878547,
   "lon": -111.858031,
   "date": "2026-05-06",
   "weight": 20.0
  },
  {
   "lat": 33.644893,
   "lon": -112.395034,
   "date": "2026-05-06",
   "weight": 1.0
  },
  {
   "lat": 33.433545,
   "lon": -111.8504,
   "date": "2026-05-06",
   "weight": 52.0
  },
  {
   "lat": 33.42744,
   "lon": -111.934004,
   "date": "2026-05-06",
   "weight": 91.0
  },
  {
   "lat": 35.189512,
   "lon": -111.654712,
   "date": "2026-05-06",
   "weight": 3.0
  },
  {
   "lat": 33.352445,
   "lon": -111.812562,
   "date": "2026-05-06",
   "weight": 23.0
  },
  {
   "lat": 33.192391,
   "lon": -111.66594,
   "date": "2026-05-06",
   "weight": 7.0
  },
  {
   "lat": 33.352445,
   "lon": -111.812562,
   "date": "2026-05-07",
   "weight": 7.0
  },
  {
   "lat": 33.192391,
   "lon": -111.66594,
   "date": "2026-05-07",
   "weight": 15.0
  },
  {
   "lat": 33.42744,
   "lon": -111.934004,
   "date": "2026-05-07",
   "weight": 255.0
  },
  {
   "lat": 33.644893,
   "lon": -112.395034,
   "date": "2026-05-07",
   "weight": 15.0
  },
  {
   "lat": 33.433545,
   "lon": -111.8504,
   "date": "2026-05-07",
   "weight": 71.0
  },
  {
   "lat": 34.598251,
   "lon": -112.33074,
   "date": "2026-05-07",
   "weight": 4.0
  },
  {
   "lat": 33.317828,
   "lon": -111.830541,
   "date": "2026-05-07",
   "weight": 32.0
  },
  {
   "lat": 35.189512,
   "lon": -111.654712,
   "date": "2026-05-07",
   "weight": 28.0
  },
  {
   "lat": 32.231069,
   "lon": -110.949568,
   "date": "2026-05-07",
   "weight": 2.0
  },
  {
   "lat": 34.878547,
   "lon": -111.858031,
   "date": "2026-05-07",
   "weight": 28.0
  },
  {
   "lat": 33.644893,
   "lon": -112.395034,
   "date": "2026-05-08",
   "weight": 29.0
  },
  {
   "lat": 33.433545,
   "lon": -111.8504,
   "date": "2026-05-08",
   "weight": 109.0
  },
  {
   "lat": 33.419233,
   "lon": -112.326866,
   "date": "2026-05-08",
   "weight": 9.0
  },
  {
   "lat": 33.317828,
   "lon": -111.830541,
   "date": "2026-05-08",
   "weight": 20.0
  },
  {
   "lat": 32.217037,
   "lon": -110.971338,
   "date": "2026-05-08",
   "weight": 5.0
  },
  {
   "lat": 34.878547,
   "lon": -111.858031,
   "date": "2026-05-08",
   "weight": 21.0
  },
  {
   "lat": 33.192391,
   "lon": -111.66594,
   "date": "2026-05-08",
   "weight": 13.0
  },
  {
   "lat": 35.189512,
   "lon": -111.654712,
   "date": "2026-05-08",
   "weight": 19.0
  },
  {
   "lat": 32.231069,
   "lon": -110.949568,
   "date": "2026-05-08",
   "weight": 1.0
  },
  {
   "lat": 33.352445,
   "lon": -111.812562,
   "date": "2026-05-08",
   "weight": 6.0
  },
  {
   "lat": 33.42744,
   "lon": -111.934004,
   "date": "2026-05-08",
   "weight": 192.0
  },
  {
   "lat": 35.189512,
   "lon": -111.654712,
   "date": "2026-05-09",
   "weight": 7.0
  },
  {
   "lat": 32.231069,
   "lon": -110.949568,
   "date": "2026-05-09",
   "weight": 14.0
  },
  {
   "lat": 33.192391,
   "lon": -111.66594,
   "date": "2026-05-09",
   "weight": 6.0
  },
  {
   "lat": 33.42744,
   "lon": -111.934004,
   "date": "2026-05-09",
   "weight": 54.0
  },
  {
   "lat": 33.644893,
   "lon": -112.395034,
   "date": "2026-05-09",
   "weight": 13.0
  },
  {
   "lat": 33.433545,
   "lon": -111.8504,
   "date": "2026-05-09",
   "weight": 21.0
  },
  {
   "lat": 33.352445,
   "lon": -111.812562,
   "date": "2026-05-09",
   "weight": 4.0
  },
  {
   "lat": 33.572326,
   "lon": -112.248142,
   "date": "2026-05-09",
   "weight": 2.0
  },
  {
   "lat": 32.217037,
   "lon": -110.971338,
   "date": "2026-05-09",
   "weight": 3.0
  },
  {
   "lat": 34.878547,
   "lon": -111.858031,
   "date": "2026-05-09",
   "weight": 8.0
  },
  {
   "lat": 33.419233,
   "lon": -112.326866,
   "date": "2026-05-09",
   "weight": 1.0
  },
  {
   "lat": 33.317828,
   "lon": -111.830541,
   "date": "2026-05-09",
   "weight": 14.0
  },
  {
   "lat": 33.352445,
   "lon": -111.812562,
   "date": "2026-05-10",
   "weight": 20.0
  },
  {
   "lat": 33.192391,
   "lon": -111.66594,
   "date": "2026-05-10",
   "weight": 8.0
  },
  {
   "lat": 33.42744,
   "lon": -111.934004,
   "date": "2026-05-10",
   "weight": 69.0
  },
  {
   "lat": 33.644893,
   "lon": -112.395034,
   "date": "2026-05-10",
   "weight": 21.0
  },
  {
   "lat": 33.433545,
   "lon": -111.8504,
   "date": "2026-05-10",
   "weight": 9.0
  },
  {
   "lat": 33.317828,
   "lon": -111.830541,
   "date": "2026-05-10",
   "weight": 14.0
  },
  {
   "lat": 35.189512,
   "lon": -111.654712,
   "date": "2026-05-10",
   "weight": 4.0
  },
  {
   "lat": 32.231069,
   "lon": -110.949568,
   "date": "2026-05-10",
   "weight": 34.0
  },
  {
   "lat": 32.217037,
   "lon": -110.971338,
   "date": "2026-05-10",
   "weight": 4.0
  },
  {
   "lat": 34.878547,
   "lon": -111.858031,
   "date": "2026-05-10",
   "weight": 23.0
  },
  {
   "lat": 33.572326,
   "lon": -112.248142,
   "date": "2026-05-10",
   "weight": 1.0
  },
  {
   "lat": 33.42744,
   "lon": -111.934004,
   "date": "2026-05-11",
   "weight": 84.0
  },
  {
   "lat": 35.189512,
   "lon": -111.654712,
   "date": "2026-05-11",
   "weight": 5.0
  },
  {
   "lat": 32.231069,
   "lon": -110.949568,
   "date": "2026-05-11",
   "weight": 30.0
  },
  {
   "lat": 33.352445,
   "lon": -111.812562,
   "date": "2026-05-11",
   "weight": 1.0
  },
  {
   "lat": 33.192391,
   "lon": -111.66594,
   "date": "2026-05-11",
   "weight": 3.0
  },
  {
   "lat": 33.644893,
   "lon": -112.395034,
   "date": "2026-05-11",
   "weight": 15.0
  },
  {
   "lat": 33.433545,
   "lon": -111.8504,
   "date": "2026-05-11",
   "weight": 70.0
  },
  {
   "lat": 34.878547,
   "lon": -111.858031,
   "date": "2026-05-11",
   "weight": 38.0
  },
  {
   "lat": 32.923874,
   "lon": -112.206708,
   "date": "2026-05-11",
   "weight": 2.0
  },
  {
   "lat": 33.317828,
   "lon": -111.830541,
   "date": "2026-05-11",
   "weight": 33.0
  },
  {
   "lat": 33.572326,
   "lon": -112.248142,
   "date": "2026-05-11",
   "weight": 2.0
  },
  {
   "lat": 33.572326,
   "lon": -112.248142,
   "date": "2026-05-12",
   "weight": 1.0
  },
  {
   "lat": 32.217037,
   "lon": -110.971338,
   "date": "2026-05-12",
   "weight": 2.0
  },
  {
   "lat": 34.878547,
   "lon": -111.858031,
   "date": "2026-05-12",
   "weight": 13.0
  },
  {
   "lat": 33.644893,
   "lon": -112.395034,
   "date": "2026-05-12",
   "weight": 4.0
  },
  {
   "lat": 33.433545,
   "lon": -111.8504,
   "date": "2026-05-12",
   "weight": 80.0
  },
  {
   "lat": 33.317828,
   "lon": -111.830541,
   "date": "2026-05-12",
   "weight": 31.0
  },
  {
   "lat": 33.42744,
   "lon": -111.934004,
   "date": "2026-05-12",
   "weight": 152.0
  },
  {
   "lat": 33.352445,
   "lon": -111.812562,
   "date": "2026-05-12",
   "weight": 2.0
  },
  {
   "lat": 35.189512,
   "lon": -111.654712,
   "date": "2026-05-12",
   "weight": 4.0
  },
  {
   "lat": 32.231069,
   "lon": -110.949568,
   "date": "2026-05-12",
   "weight": 8.0
  },
  {
   "lat": 33.192391,
   "lon": -111.66594,
   "date": "2026-05-12",
   "weight": 2.0
  },
  {
   "lat": 32.217037,
   "lon": -110.971338,
   "date": "2026-05-13",
   "weight": 1.0
  },
  {
   "lat": 34.878547,
   "lon": -111.858031,
   "date": "2026-05-13",
   "weight": 9.0
  },
  {
   "lat": 33.317828,
   "lon": -111.830541,
   "date": "2026-05-13",
   "weight": 17.0
  },
  {
   "lat": 33.644893,
   "lon": -112.395034,
   "date": "2026-05-13",
   "weight": 16.0
  },
  {
   "lat": 33.433545,
   "lon": -111.8504,
   "date": "2026-05-13",
   "weight": 55.0
  },
  {
   "lat": 33.192391,
   "lon": -111.66594,
   "date": "2026-05-13",
   "weight": 5.0
  },
  {
   "lat": 33.42744,
   "lon": -111.934004,
   "date": "2026-05-13",
   "weight": 151.0
  },
  {
   "lat": 33.572326,
   "lon": -112.248142,
   "date": "2026-05-13",
   "weight": 3.0
  },
  {
   "lat": 33.352445,
   "lon": -111.812562,
   "date": "2026-05-13",
   "weight": 107.0
  },
  {
   "lat": 35.189512,
   "lon": -111.654712,
   "date": "2026-05-13",
   "weight": 6.0
  },
  {
   "lat": 32.231069,
   "lon": -110.949568,
   "date": "2026-05-13",
   "weight": 14.0
  },
  {
   "lat": 33.42744,
   "lon": -111.934004,
   "date": "2026-05-14",
   "weight": 113.0
  },
  {
   "lat": 35.189512,
   "lon": -111.654712,
   "date": "2026-05-14",
   "weight": 4.0
  },
  {
   "lat": 32.231069,
   "lon": -110.949568,
   "date": "2026-05-14",
   "weight": 14.0
  },
  {
   "lat": 33.352445,
   "lon": -111.812562,
   "date": "2026-05-14",
   "weight": 31.0
  },
  {
   "lat": 33.192391,
   "lon": -111.66594,
   "date": "2026-05-14",
   "weight": 1.0
  },
  {
   "lat": 33.644893,
   "lon": -112.395034,
   "date": "2026-05-14",
   "weight": 16.0
  },
  {
   "lat": 33.433545,
   "lon": -111.8504,
   "date": "2026-05-14",
   "weight": 64.0
  },
  {
   "lat": 32.217037,
   "lon": -110.971338,
   "date": "2026-05-14",
   "weight": 2.0
  },
  {
   "lat": 34.878547,
   "lon": -111.858031,
   "date": "2026-05-14",
   "weight": 11.0
  },
  {
   "lat": 32.923874,
   "lon": -112.206708,
   "date": "2026-05-14",
   "weight": 6.0
  },
  {
   "lat": 33.317828,
   "lon": -111.830541,
   "date": "2026-05-14",
   "weight": 13.0
  },
  {
   "lat": 33.572326,
   "lon": -112.248142,
   "date": "2026-05-15",
   "weight": 1.0
  },
  {
   "lat": 34.878547,
   "lon": -111.858031,
   "date": "2026-05-15",
   "weight": 50.0
  },
  {
   "lat": 33.644893,
   "lon": -112.395034,
   "date": "2026-05-15",
   "weight": 13.0
  },
  {
   "lat": 33.433545,
   "lon": -111.8504,
   "date": "2026-05-15",
   "weight": 59.0
  },
  {
   "lat": 32.923874,
   "lon": -112.206708,
   "date": "2026-05-15",
   "weight": 1.0
  },
  {
   "lat": 33.317828,
   "lon": -111.830541,
   "date": "2026-05-15",
   "weight": 38.0
  },
  {
   "lat": 33.42744,
   "lon": -111.934004,
   "date": "2026-05-15",
   "weight": 82.0
  },
  {
   "lat": 33.352445,
   "lon": -111.812562,
   "date": "2026-05-15",
   "weight": 24.0
  },
  {
   "lat": 35.189512,
   "lon": -111.654712,
   "date": "2026-05-15",
   "weight": 5.0
  },
  {
   "lat": 32.231069,
   "lon": -110.949568,
   "date": "2026-05-15",
   "weight": 5.0
  },
  {
   "lat": 33.192391,
   "lon": -111.66594,
   "date": "2026-05-15",
   "weight": 1.0
  },
  {
   "lat": 33.644893,
   "lon": -112.395034,
   "date": "2026-05-16",
   "weight": 9.0
  },
  {
   "lat": 33.433545,
   "lon": -111.8504,
   "date": "2026-05-16",
   "weight": 65.0
  },
  {
   "lat": 34.598251,
   "lon": -112.33074,
   "date": "2026-05-16",
   "weight": 2.0
  },
  {
   "lat": 33.317828,
   "lon": -111.830541,
   "date": "2026-05-16",
   "weight": 23.0
  },
  {
   "lat": 33.248065,
   "lon": -111.489238,
   "date": "2026-05-16",
   "weight": 1.0
  },
  {
   "lat": 34.878547,
   "lon": -111.858031,
   "date": "2026-05-16",
   "weight": 15.0
  },
  {
   "lat": 33.192391,
   "lon": -111.66594,
   "date": "2026-05-16",
   "weight": 3.0
  },
  {
   "lat": 35.189512,
   "lon": -111.654712,
   "date": "2026-05-16",
   "weight": 5.0
  },
  {
   "lat": 32.231069,
   "lon": -110.949568,
   "date": "2026-05-16",
   "weight": 36.0
  },
  {
   "lat": 33.352445,
   "lon": -111.812562,
   "date": "2026-05-16",
   "weight": 19.0
  },
  {
   "lat": 33.42744,
   "lon": -111.934004,
   "date": "2026-05-16",
   "weight": 57.0
  },
  {
   "lat": 33.42744,
   "lon": -111.934004,
   "date": "2026-05-17",
   "weight": 42.0
  },
  {
   "lat": 33.352445,
   "lon": -111.812562,
   "date": "2026-05-17",
   "weight": 17.0
  },
  {
   "lat": 35.189512,
   "lon": -111.654712,
   "date": "2026-05-17",
   "weight": 1.0
  },
  {
   "lat": 32.231069,
   "lon": -110.949568,
   "date": "2026-05-17",
   "weight": 31.0
  },
  {
   "lat": 32.923874,
   "lon": -112.206708,
   "date": "2026-05-17",
   "weight": 2.0
  },
  {
   "lat": 33.317828,
   "lon": -111.830541,
   "date": "2026-05-17",
   "weight": 22.0
  },
  {
   "lat": 33.192391,
   "lon": -111.66594,
   "date": "2026-05-17",
   "weight": 10.0
  },
  {
   "lat": 32.217037,
   "lon": -110.971338,
   "date": "2026-05-17",
   "weight": 2.0
  },
  {
   "lat": 34.878547,
   "lon": -111.858031,
   "date": "2026-05-17",
   "weight": 6.0
  },
  {
   "lat": 33.644893,
   "lon": -112.395034,
   "date": "2026-05-17",
   "weight": 5.0
  },
  {
   "lat": 33.433545,
   "lon": -111.8504,
   "date": "2026-05-17",
   "weight": 50.0
  },
  {
   "lat": 32.923874,
   "lon": -112.206708,
   "date": "2026-05-18",
   "weight": 24.0
  },
  {
   "lat": 33.317828,
   "lon": -111.830541,
   "date": "2026-05-18",
   "weight": 23.0
  },
  {
   "lat": 32.217037,
   "lon": -110.971338,
   "date": "2026-05-18",
   "weight": 10.0
  },
  {
   "lat": 34.878547,
   "lon": -111.858031,
   "date": "2026-05-18",
   "weight": 34.0
  },
  {
   "lat": 33.644893,
   "lon": -112.395034,
   "date": "2026-05-18",
   "weight": 2.0
  },
  {
   "lat": 33.433545,
   "lon": -111.8504,
   "date": "2026-05-18",
   "weight": 85.0
  },
  {
   "lat": 33.42744,
   "lon": -111.934004,
   "date": "2026-05-18",
   "weight": 69.0
  },
  {
   "lat": 32.231069,
   "lon": -110.949568,
   "date": "2026-05-18",
   "weight": 17.0
  },
  {
   "lat": 33.352445,
   "lon": -111.812562,
   "date": "2026-05-18",
   "weight": 6.0
  },
  {
   "lat": 33.192391,
   "lon": -111.66594,
   "date": "2026-05-18",
   "weight": 7.0
  },
  {
   "lat": 33.644893,
   "lon": -112.395034,
   "date": "2026-05-19",
   "weight": 3.0
  },
  {
   "lat": 33.433545,
   "lon": -111.8504,
   "date": "2026-05-19",
   "weight": 48.0
  },
  {
   "lat": 32.923874,
   "lon": -112.206708,
   "date": "2026-05-19",
   "weight": 1.0
  },
  {
   "lat": 33.317828,
   "lon": -111.830541,
   "date": "2026-05-19",
   "weight": 24.0
  },
  {
   "lat": 33.248065,
   "lon": -111.489238,
   "date": "2026-05-19",
   "weight": 1.0
  },
  {
   "lat": 32.217037,
   "lon": -110.971338,
   "date": "2026-05-19",
   "weight": 3.0
  },
  {
   "lat": 34.878547,
   "lon": -111.858031,
   "date": "2026-05-19",
   "weight": 50.0
  },
  {
   "lat": 33.192391,
   "lon": -111.66594,
   "date": "2026-05-19",
   "weight": 7.0
  },
  {
   "lat": 35.189512,
   "lon": -111.654712,
   "date": "2026-05-19",
   "weight": 5.0
  },
  {
   "lat": 32.231069,
   "lon": -110.949568,
   "date": "2026-05-19",
   "weight": 18.0
  },
  {
   "lat": 33.352445,
   "lon": -111.812562,
   "date": "2026-05-19",
   "weight": 2.0
  },
  {
   "lat": 33.42744,
   "lon": -111.934004,
   "date": "2026-05-19",
   "weight": 79.0
  },
  {
   "lat": 32.923874,
   "lon": -112.206708,
   "date": "2026-05-20",
   "weight": 9.0
  },
  {
   "lat": 33.317828,
   "lon": -111.830541,
   "date": "2026-05-20",
   "weight": 13.0
  },
  {
   "lat": 33.644893,
   "lon": -112.395034,
   "date": "2026-05-20",
   "weight": 1.0
  },
  {
   "lat": 33.433545,
   "lon": -111.8504,
   "date": "2026-05-20",
   "weight": 85.0
  },
  {
   "lat": 32.217037,
   "lon": -110.971338,
   "date": "2026-05-20",
   "weight": 2.0
  },
  {
   "lat": 34.878547,
   "lon": -111.858031,
   "date": "2026-05-20",
   "weight": 63.0
  },
  {
   "lat": 33.248065,
   "lon": -111.489238,
   "date": "2026-05-20",
   "weight": 2.0
  },
  {
   "lat": 33.192391,
   "lon": -111.66594,
   "date": "2026-05-20",
   "weight": 2.0
  },
  {
   "lat": 33.42744,
   "lon": -111.934004,
   "date": "2026-05-20",
   "weight": 56.0
  },
  {
   "lat": 35.189512,
   "lon": -111.654712,
   "date": "2026-05-20",
   "weight": 18.0
  },
  {
   "lat": 32.231069,
   "lon": -110.949568,
   "date": "2026-05-20",
   "weight": 6.0
  },
  {
   "lat": 32.217037,
   "lon": -110.971338,
   "date": "2026-05-21",
   "weight": 2.0
  },
  {
   "lat": 34.878547,
   "lon": -111.858031,
   "date": "2026-05-21",
   "weight": 46.0
  },
  {
   "lat": 33.317828,
   "lon": -111.830541,
   "date": "2026-05-21",
   "weight": 28.0
  },
  {
   "lat": 33.433545,
   "lon": -111.8504,
   "date": "2026-05-21",
   "weight": 55.0
  },
  {
   "lat": 33.192391,
   "lon": -111.66594,
   "date": "2026-05-21",
   "weight": 2.0
  },
  {
   "lat": 33.42744,
   "lon": -111.934004,
   "date": "2026-05-21",
   "weight": 70.0
  },
  {
   "lat": 33.248065,
   "lon": -111.489238,
   "date": "2026-05-21",
   "weight": 1.0
  },
  {
   "lat": 35.189512,
   "lon": -111.654712,
   "date": "2026-05-21",
   "weight": 11.0
  },
  {
   "lat": 32.231069,
   "lon": -110.949568,
   "date": "2026-05-21",
   "weight": 5.0
  },
  {
   "lat": 32.217037,
   "lon": -110.971338,
   "date": "2026-05-22",
   "weight": 2.0
  },
  {
   "lat": 34.878547,
   "lon": -111.858031,
   "date": "2026-05-22",
   "weight": 28.0
  },
  {
   "lat": 32.923874,
   "lon": -112.206708,
   "date": "2026-05-22",
   "weight": 4.0
  },
  {
   "lat": 33.317828,
   "lon": -111.830541,
   "date": "2026-05-22",
   "weight": 29.0
  },
  {
   "lat": 33.644893,
   "lon": -112.395034,
   "date": "2026-05-22",
   "weight": 13.0
  },
  {
   "lat": 33.433545,
   "lon": -111.8504,
   "date": "2026-05-22",
   "weight": 34.0
  },
  {
   "lat": 33.192391,
   "lon": -111.66594,
   "date": "2026-05-22",
   "weight": 1.0
  },
  {
   "lat": 33.42744,
   "lon": -111.934004,
   "date": "2026-05-22",
   "weight": 82.0
  },
  {
   "lat": 33.572326,
   "lon": -112.248142,
   "date": "2026-05-22",
   "weight": 2.0
  },
  {
   "lat": 33.352445,
   "lon": -111.812562,
   "date": "2026-05-22",
   "weight": 2.0
  },
  {
   "lat": 35.189512,
   "lon": -111.654712,
   "date": "2026-05-22",
   "weight": 8.0
  },
  {
   "lat": 32.231069,
   "lon": -110.949568,
   "date": "2026-05-22",
   "weight": 2.0
  },
  {
   "lat": 33.572326,
   "lon": -112.248142,
   "date": "2026-05-23",
   "weight": 2.0
  },
  {
   "lat": 32.217037,
   "lon": -110.971338,
   "date": "2026-05-23",
   "weight": 1.0
  },
  {
   "lat": 34.878547,
   "lon": -111.858031,
   "date": "2026-05-23",
   "weight": 17.0
  },
  {
   "lat": 33.644893,
   "lon": -112.395034,
   "date": "2026-05-23",
   "weight": 13.0
  },
  {
   "lat": 33.433545,
   "lon": -111.8504,
   "date": "2026-05-23",
   "weight": 15.0
  },
  {
   "lat": 33.317828,
   "lon": -111.830541,
   "date": "2026-05-23",
   "weight": 19.0
  },
  {
   "lat": 33.42744,
   "lon": -111.934004,
   "date": "2026-05-23",
   "weight": 51.0
  },
  {
   "lat": 33.352445,
   "lon": -111.812562,
   "date": "2026-05-23",
   "weight": 1.0
  },
  {
   "lat": 35.189512,
   "lon": -111.654712,
   "date": "2026-05-23",
   "weight": 10.0
  },
  {
   "lat": 33.192391,
   "lon": -111.66594,
   "date": "2026-05-23",
   "weight": 14.0
  },
  {
   "lat": 32.217037,
   "lon": -110.971338,
   "date": "2026-05-24",
   "weight": 1.0
  },
  {
   "lat": 34.878547,
   "lon": -111.858031,
   "date": "2026-05-24",
   "weight": 67.0
  },
  {
   "lat": 32.923874,
   "lon": -112.206708,
   "date": "2026-05-24",
   "weight": 2.0
  },
  {
   "lat": 33.317828,
   "lon": -111.830541,
   "date": "2026-05-24",
   "weight": 11.0
  },
  {
   "lat": 33.572326,
   "lon": -112.248142,
   "date": "2026-05-24",
   "weight": 1.0
  },
  {
   "lat": 33.352445,
   "lon": -111.812562,
   "date": "2026-05-24",
   "weight": 7.0
  },
  {
   "lat": 35.189512,
   "lon": -111.654712,
   "date": "2026-05-24",
   "weight": 5.0
  },
  {
   "lat": 32.231069,
   "lon": -110.949568,
   "date": "2026-05-24",
   "weight": 2.0
  },
  {
   "lat": 33.644893,
   "lon": -112.395034,
   "date": "2026-05-24",
   "weight": 4.0
  },
  {
   "lat": 33.433545,
   "lon": -111.8504,
   "date": "2026-05-24",
   "weight": 80.0
  },
  {
   "lat": 33.42744,
   "lon": -111.934004,
   "date": "2026-05-24",
   "weight": 52.0
  },
  {
   "lat": 33.192391,
   "lon": -111.66594,
   "date": "2026-05-24",
   "weight": 5.0
  },
  {
   "lat": 34.878547,
   "lon": -111.858031,
   "date": "2026-05-25",
   "weight": 14.0
  },
  {
   "lat": 32.923874,
   "lon": -112.206708,
   "date": "2026-05-25",
   "weight": 2.0
  },
  {
   "lat": 33.317828,
   "lon": -111.830541,
   "date": "2026-05-25",
   "weight": 39.0
  },
  {
   "lat": 33.644893,
   "lon": -112.395034,
   "date": "2026-05-25",
   "weight": 2.0
  },
  {
   "lat": 33.433545,
   "lon": -111.8504,
   "date": "2026-05-25",
   "weight": 130.0
  },
  {
   "lat": 33.192391,
   "lon": -111.66594,
   "date": "2026-05-25",
   "weight": 5.0
  },
  {
   "lat": 33.42744,
   "lon": -111.934004,
   "date": "2026-05-25",
   "weight": 47.0
  },
  {
   "lat": 33.572326,
   "lon": -112.248142,
   "date": "2026-05-25",
   "weight": 1.0
  },
  {
   "lat": 33.248065,
   "lon": -111.489238,
   "date": "2026-05-25",
   "weight": 1.0
  },
  {
   "lat": 33.352445,
   "lon": -111.812562,
   "date": "2026-05-25",
   "weight": 40.0
  },
  {
   "lat": 35.189512,
   "lon": -111.654712,
   "date": "2026-05-25",
   "weight": 4.0
  },
  {
   "lat": 32.231069,
   "lon": -110.949568,
   "date": "2026-05-25",
   "weight": 4.0
  },
  {
   "lat": 33.42744,
   "lon": -111.934004,
   "date": "2026-05-26",
   "weight": 66.0
  },
  {
   "lat": 33.352445,
   "lon": -111.812562,
   "date": "2026-05-26",
   "weight": 25.0
  },
  {
   "lat": 35.189512,
   "lon": -111.654712,
   "date": "2026-05-26",
   "weight": 16.0
  },
  {
   "lat": 32.231069,
   "lon": -110.949568,
   "date": "2026-05-26",
   "weight": 4.0
  },
  {
   "lat": 32.923874,
   "lon": -112.206708,
   "date": "2026-05-26",
   "weight": 1.0
  },
  {
   "lat": 33.317828,
   "lon": -111.830541,
   "date": "2026-05-26",
   "weight": 62.0
  },
  {
   "lat": 33.192391,
   "lon": -111.66594,
   "date": "2026-05-26",
   "weight": 2.0
  },
  {
   "lat": 32.217037,
   "lon": -110.971338,
   "date": "2026-05-26",
   "weight": 5.0
  },
  {
   "lat": 34.878547,
   "lon": -111.858031,
   "date": "2026-05-26",
   "weight": 17.0
  },
  {
   "lat": 33.644893,
   "lon": -112.395034,
   "date": "2026-05-26",
   "weight": 2.0
  },
  {
   "lat": 33.433545,
   "lon": -111.8504,
   "date": "2026-05-26",
   "weight": 78.0
  },
  {
   "lat": 33.192391,
   "lon": -111.66594,
   "date": "2026-05-27",
   "weight": 3.0
  },
  {
   "lat": 35.189512,
   "lon": -111.654712,
   "date": "2026-05-27",
   "weight": 4.0
  },
  {
   "lat": 32.231069,
   "lon": -110.949568,
   "date": "2026-05-27",
   "weight": 1.0
  },
  {
   "lat": 33.352445,
   "lon": -111.812562,
   "date": "2026-05-27",
   "weight": 15.0
  },
  {
   "lat": 33.42744,
   "lon": -111.934004,
   "date": "2026-05-27",
   "weight": 83.0
  },
  {
   "lat": 32.923874,
   "lon": -112.206708,
   "date": "2026-05-27",
   "weight": 1.0
  },
  {
   "lat": 33.317828,
   "lon": -111.830541,
   "date": "2026-05-27",
   "weight": 30.0
  },
  {
   "lat": 32.217037,
   "lon": -110.971338,
   "date": "2026-05-27",
   "weight": 11.0
  },
  {
   "lat": 34.878547,
   "lon": -111.858031,
   "date": "2026-05-27",
   "weight": 5.0
  },
  {
   "lat": 33.644893,
   "lon": -112.395034,
   "date": "2026-05-27",
   "weight": 7.0
  },
  {
   "lat": 33.433545,
   "lon": -111.8504,
   "date": "2026-05-27",
   "weight": 49.0
  },
  {
   "lat": 33.572326,
   "lon": -112.248142,
   "date": "2026-05-27",
   "weight": 2.0
  },
  {
   "lat": 33.644893,
   "lon": -112.395034,
   "date": "2026-05-28",
   "weight": 2.0
  },
  {
   "lat": 33.433545,
   "lon": -111.8504,
   "date": "2026-05-28",
   "weight": 32.0
  },
  {
   "lat": 33.317828,
   "lon": -111.830541,
   "date": "2026-05-28",
   "weight": 28.0
  },
  {
   "lat": 32.217037,
   "lon": -110.971338,
   "date": "2026-05-28",
   "weight": 15.0
  },
  {
   "lat": 34.878547,
   "lon": -111.858031,
   "date": "2026-05-28",
   "weight": 15.0
  },
  {
   "lat": 35.189512,
   "lon": -111.654712,
   "date": "2026-05-28",
   "weight": 13.0
  },
  {
   "lat": 32.231069,
   "lon": -110.949568,
   "date": "2026-05-28",
   "weight": 7.0
  },
  {
   "lat": 33.352445,
   "lon": -111.812562,
   "date": "2026-05-28",
   "weight": 6.0
  },
  {
   "lat": 33.42744,
   "lon": -111.934004,
   "date": "2026-05-28",
   "weight": 33.0
  },
  {
   "lat": 33.192391,
   "lon": -111.66594,
   "date": "2026-05-28",
   "weight": 8.0
  },
  {
   "lat": 33.433545,
   "lon": -111.8504,
   "date": "2026-05-29",
   "weight": 58.0
  },
  {
   "lat": 33.317828,
   "lon": -111.830541,
   "date": "2026-05-29",
   "weight": 89.0
  },
  {
   "lat": 33.248065,
   "lon": -111.489238,
   "date": "2026-05-29",
   "weight": 1.0
  },
  {
   "lat": 32.217037,
   "lon": -110.971338,
   "date": "2026-05-29",
   "weight": 4.0
  },
  {
   "lat": 34.878547,
   "lon": -111.858031,
   "date": "2026-05-29",
   "weight": 9.0
  },
  {
   "lat": 33.192391,
   "lon": -111.66594,
   "date": "2026-05-29",
   "weight": 1.0
  },
  {
   "lat": 35.189512,
   "lon": -111.654712,
   "date": "2026-05-29",
   "weight": 9.0
  },
  {
   "lat": 32.231069,
   "lon": -110.949568,
   "date": "2026-05-29",
   "weight": 16.0
  },
  {
   "lat": 33.352445,
   "lon": -111.812562,
   "date": "2026-05-29",
   "weight": 6.0
  },
  {
   "lat": 33.42744,
   "lon": -111.934004,
   "date": "2026-05-29",
   "weight": 25.0
  },
  {
   "lat": 33.317828,
   "lon": -111.830541,
   "date": "2026-05-30",
   "weight": 33.0
  },
  {
   "lat": 33.433545,
   "lon": -111.8504,
   "date": "2026-05-30",
   "weight": 90.0
  },
  {
   "lat": 32.217037,
   "lon": -110.971338,
   "date": "2026-05-30",
   "weight": 5.0
  },
  {
   "lat": 34.878547,
   "lon": -111.858031,
   "date": "2026-05-30",
   "weight": 19.0
  },
  {
   "lat": 33.248065,
   "lon": -111.489238,
   "date": "2026-05-30",
   "weight": 4.0
  },
  {
   "lat": 33.192391,
   "lon": -111.66594,
   "date": "2026-05-30",
   "weight": 5.0
  },
  {
   "lat": 33.352445,
   "lon": -111.812562,
   "date": "2026-05-30",
   "weight": 44.0
  },
  {
   "lat": 33.42744,
   "lon": -111.934004,
   "date": "2026-05-30",
   "weight": 44.0
  },
  {
   "lat": 35.189512,
   "lon": -111.654712,
   "date": "2026-05-30",
   "weight": 6.0
  },
  {
   "lat": 32.231069,
   "lon": -110.949568,
   "date": "2026-05-30",
   "weight": 1.0
  },
  {
   "lat": 32.217037,
   "lon": -110.971338,
   "date": "2026-05-31",
   "weight": 2.0
  },
  {
   "lat": 34.878547,
   "lon": -111.858031,
   "date": "2026-05-31",
   "weight": 6.0
  },
  {
   "lat": 33.317828,
   "lon": -111.830541,
   "date": "2026-05-31",
   "weight": 13.0
  },
  {
   "lat": 33.644893,
   "lon": -112.395034,
   "date": "2026-05-31",
   "weight": 6.0
  },
  {
   "lat": 33.433545,
   "lon": -111.8504,
   "date": "2026-05-31",
   "weight": 81.0
  },
  {
   "lat": 33.192391,
   "lon": -111.66594,
   "date": "2026-05-31",
   "weight": 2.0
  },
  {
   "lat": 33.42744,
   "lon": -111.934004,
   "date": "2026-05-31",
   "weight": 10.0
  },
  {
   "lat": 33.248065,
   "lon": -111.489238,
   "date": "2026-05-31",
   "weight": 2.0
  },
  {
   "lat": 33.352445,
   "lon": -111.812562,
   "date": "2026-05-31",
   "weight": 32.0
  },
  {
   "lat": 35.189512,
   "lon": -111.654712,
   "date": "2026-05-31",
   "weight": 7.0
  },
  {
   "lat": 32.231069,
   "lon": -110.949568,
   "date": "2026-05-31",
   "weight": 3.0
  },
  {
   "lat": 33.352445,
   "lon": -111.812562,
   "date": "2026-06-01",
   "weight": 38.0
  },
  {
   "lat": 33.42744,
   "lon": -111.934004,
   "date": "2026-06-01",
   "weight": 25.0
  },
  {
   "lat": 33.192391,
   "lon": -111.66594,
   "date": "2026-06-01",
   "weight": 2.0
  },
  {
   "lat": 33.248065,
   "lon": -111.489238,
   "date": "2026-06-01",
   "weight": 1.0
  },
  {
   "lat": 35.189512,
   "lon": -111.654712,
   "date": "2026-06-01",
   "weight": 24.0
  },
  {
   "lat": 32.231069,
   "lon": -110.949568,
   "date": "2026-06-01",
   "weight": 36.0
  },
  {
   "lat": 32.217037,
   "lon": -110.971338,
   "date": "2026-06-01",
   "weight": 3.0
  },
  {
   "lat": 34.878547,
   "lon": -111.858031,
   "date": "2026-06-01",
   "weight": 51.0
  },
  {
   "lat": 33.419233,
   "lon": -112.326866,
   "date": "2026-06-01",
   "weight": 1.0
  },
  {
   "lat": 33.317828,
   "lon": -111.830541,
   "date": "2026-06-01",
   "weight": 17.0
  },
  {
   "lat": 33.644893,
   "lon": -112.395034,
   "date": "2026-06-01",
   "weight": 6.0
  },
  {
   "lat": 33.433545,
   "lon": -111.8504,
   "date": "2026-06-01",
   "weight": 71.0
  },
  {
   "lat": 34.598251,
   "lon": -112.33074,
   "date": "2026-06-01",
   "weight": 1.0
  },
  {
   "lat": 33.42744,
   "lon": -111.934004,
   "date": "2026-06-02",
   "weight": 20.0
  },
  {
   "lat": 33.352445,
   "lon": -111.812562,
   "date": "2026-06-02",
   "weight": 14.0
  },
  {
   "lat": 35.189512,
   "lon": -111.654712,
   "date": "2026-06-02",
   "weight": 4.0
  },
  {
   "lat": 32.231069,
   "lon": -110.949568,
   "date": "2026-06-02",
   "weight": 12.0
  },
  {
   "lat": 33.317828,
   "lon": -111.830541,
   "date": "2026-06-02",
   "weight": 19.0
  },
  {
   "lat": 33.192391,
   "lon": -111.66594,
   "date": "2026-06-02",
   "weight": 12.0
  },
  {
   "lat": 32.217037,
   "lon": -110.971338,
   "date": "2026-06-02",
   "weight": 1.0
  },
  {
   "lat": 34.878547,
   "lon": -111.858031,
   "date": "2026-06-02",
   "weight": 11.0
  },
  {
   "lat": 33.644893,
   "lon": -112.395034,
   "date": "2026-06-02",
   "weight": 17.0
  },
  {
   "lat": 33.433545,
   "lon": -111.8504,
   "date": "2026-06-02",
   "weight": 108.0
  },
  {
   "lat": 33.644893,
   "lon": -112.395034,
   "date": "2026-06-03",
   "weight": 7.0
  },
  {
   "lat": 33.433545,
   "lon": -111.8504,
   "date": "2026-06-03",
   "weight": 76.0
  },
  {
   "lat": 34.598251,
   "lon": -112.33074,
   "date": "2026-06-03",
   "weight": 1.0
  },
  {
   "lat": 33.317828,
   "lon": -111.830541,
   "date": "2026-06-03",
   "weight": 8.0
  },
  {
   "lat": 34.878547,
   "lon": -111.858031,
   "date": "2026-06-03",
   "weight": 50.0
  },
  {
   "lat": 35.189512,
   "lon": -111.654712,
   "date": "2026-06-03",
   "weight": 6.0
  },
  {
   "lat": 32.231069,
   "lon": -110.949568,
   "date": "2026-06-03",
   "weight": 31.0
  },
  {
   "lat": 35.357736,
   "lon": -111.771155,
   "date": "2026-06-03",
   "weight": 5.0
  },
  {
   "lat": 33.352445,
   "lon": -111.812562,
   "date": "2026-06-03",
   "weight": 21.0
  },
  {
   "lat": 33.42744,
   "lon": -111.934004,
   "date": "2026-06-03",
   "weight": 45.0
  },
  {
   "lat": 33.192391,
   "lon": -111.66594,
   "date": "2026-06-03",
   "weight": 5.0
  },
  {
   "lat": 33.248065,
   "lon": -111.489238,
   "date": "2026-06-03",
   "weight": 1.0
  },
  {
   "lat": 33.42744,
   "lon": -111.934004,
   "date": "2026-06-04",
   "weight": 69.0
  },
  {
   "lat": 35.357736,
   "lon": -111.771155,
   "date": "2026-06-04",
   "weight": 11.0
  },
  {
   "lat": 33.352445,
   "lon": -111.812562,
   "date": "2026-06-04",
   "weight": 23.0
  },
  {
   "lat": 35.189512,
   "lon": -111.654712,
   "date": "2026-06-04",
   "weight": 6.0
  },
  {
   "lat": 32.231069,
   "lon": -110.949568,
   "date": "2026-06-04",
   "weight": 26.0
  },
  {
   "lat": 33.317828,
   "lon": -111.830541,
   "date": "2026-06-04",
   "weight": 6.0
  },
  {
   "lat": 33.572326,
   "lon": -112.248142,
   "date": "2026-06-04",
   "weight": 1.0
  },
  {
   "lat": 33.192391,
   "lon": -111.66594,
   "date": "2026-06-04",
   "weight": 2.0
  },
  {
   "lat": 34.878547,
   "lon": -111.858031,
   "date": "2026-06-04",
   "weight": 33.0
  },
  {
   "lat": 33.45052,
   "lon": -112.078343,
   "date": "2026-06-04",
   "weight": 5.0
  },
  {
   "lat": 33.644893,
   "lon": -112.395034,
   "date": "2026-06-04",
   "weight": 17.0
  },
  {
   "lat": 33.433545,
   "lon": -111.8504,
   "date": "2026-06-04",
   "weight": 42.0
  },
  {
   "lat": 33.352445,
   "lon": -111.812562,
   "date": "2026-06-05",
   "weight": 16.0
  },
  {
   "lat": 35.357736,
   "lon": -111.771155,
   "date": "2026-06-05",
   "weight": 8.0
  },
  {
   "lat": 32.704556,
   "lon": -114.656304,
   "date": "2026-06-05",
   "weight": 25.0
  },
  {
   "lat": 33.42744,
   "lon": -111.934004,
   "date": "2026-06-05",
   "weight": 28.0
  },
  {
   "lat": 33.192391,
   "lon": -111.66594,
   "date": "2026-06-05",
   "weight": 5.0
  },
  {
   "lat": 35.189512,
   "lon": -111.654712,
   "date": "2026-06-05",
   "weight": 1.0
  },
  {
   "lat": 32.231069,
   "lon": -110.949568,
   "date": "2026-06-05",
   "weight": 12.0
  },
  {
   "lat": 32.217037,
   "lon": -110.971338,
   "date": "2026-06-05",
   "weight": 329.0
  },
  {
   "lat": 34.878547,
   "lon": -111.858031,
   "date": "2026-06-05",
   "weight": 21.0
  },
  {
   "lat": 33.45052,
   "lon": -112.078343,
   "date": "2026-06-05",
   "weight": 640.0
  },
  {
   "lat": 33.494489,
   "lon": -111.920714,
   "date": "2026-06-05",
   "weight": 101.0
  },
  {
   "lat": 33.317828,
   "lon": -111.830541,
   "date": "2026-06-05",
   "weight": 48.0
  },
  {
   "lat": 34.598081,
   "lon": -112.420156,
   "date": "2026-06-05",
   "weight": 2.0
  },
  {
   "lat": 33.644893,
   "lon": -112.395034,
   "date": "2026-06-05",
   "weight": 2.0
  },
  {
   "lat": 33.433545,
   "lon": -111.8504,
   "date": "2026-06-05",
   "weight": 23.0
  },
  {
   "lat": 33.192391,
   "lon": -111.66594,
   "date": "2026-06-06",
   "weight": 1.0
  },
  {
   "lat": 35.189512,
   "lon": -111.654712,
   "date": "2026-06-06",
   "weight": 1.0
  },
  {
   "lat": 32.231069,
   "lon": -110.949568,
   "date": "2026-06-06",
   "weight": 5.0
  },
  {
   "lat": 33.352445,
   "lon": -111.812562,
   "date": "2026-06-06",
   "weight": 9.0
  },
  {
   "lat": 33.42744,
   "lon": -111.934004,
   "date": "2026-06-06",
   "weight": 31.0
  },
  {
   "lat": 35.357736,
   "lon": -111.771155,
   "date": "2026-06-06",
   "weight": 9.0
  },
  {
   "lat": 32.704556,
   "lon": -114.656304,
   "date": "2026-06-06",
   "weight": 23.0
  },
  {
   "lat": 33.317828,
   "lon": -111.830541,
   "date": "2026-06-06",
   "weight": 23.0
  },
  {
   "lat": 32.217037,
   "lon": -110.971338,
   "date": "2026-06-06",
   "weight": 191.0
  },
  {
   "lat": 34.878547,
   "lon": -111.858031,
   "date": "2026-06-06",
   "weight": 7.0
  },
  {
   "lat": 33.45052,
   "lon": -112.078343,
   "date": "2026-06-06",
   "weight": 461.0
  },
  {
   "lat": 34.598081,
   "lon": -112.420156,
   "date": "2026-06-06",
   "weight": 16.0
  },
  {
   "lat": 33.644893,
   "lon": -112.395034,
   "date": "2026-06-06",
   "weight": 2.0
  },
  {
   "lat": 33.433545,
   "lon": -111.8504,
   "date": "2026-06-06",
   "weight": 32.0
  },
  {
   "lat": 33.494489,
   "lon": -111.920714,
   "date": "2026-06-06",
   "weight": 82.0
  },
  {
   "lat": 34.878547,
   "lon": -111.858031,
   "date": "2026-06-07",
   "weight": 44.0
  },
  {
   "lat": 33.45052,
   "lon": -112.078343,
   "date": "2026-06-07",
   "weight": 299.0
  },
  {
   "lat": 33.317828,
   "lon": -111.830541,
   "date": "2026-06-07",
   "weight": 36.0
  },
  {
   "lat": 33.494489,
   "lon": -111.920714,
   "date": "2026-06-07",
   "weight": 105.0
  },
  {
   "lat": 32.217037,
   "lon": -110.971338,
   "date": "2026-06-07",
   "weight": 405.0
  },
  {
   "lat": 33.352445,
   "lon": -111.812562,
   "date": "2026-06-07",
   "weight": 66.0
  },
  {
   "lat": 33.42744,
   "lon": -111.934004,
   "date": "2026-06-07",
   "weight": 36.0
  },
  {
   "lat": 35.357736,
   "lon": -111.771155,
   "date": "2026-06-07",
   "weight": 1.0
  },
  {
   "lat": 32.704556,
   "lon": -114.656304,
   "date": "2026-06-07",
   "weight": 17.0
  },
  {
   "lat": 35.189512,
   "lon": -111.654712,
   "date": "2026-06-07",
   "weight": 6.0
  },
  {
   "lat": 32.231069,
   "lon": -110.949568,
   "date": "2026-06-07",
   "weight": 5.0
  },
  {
   "lat": 33.248065,
   "lon": -111.489238,
   "date": "2026-06-07",
   "weight": 1.0
  },
  {
   "lat": 34.598081,
   "lon": -112.420156,
   "date": "2026-06-07",
   "weight": 7.0
  },
  {
   "lat": 33.644893,
   "lon": -112.395034,
   "date": "2026-06-07",
   "weight": 20.0
  },
  {
   "lat": 33.433545,
   "lon": -111.8504,
   "date": "2026-06-07",
   "weight": 32.0
  },
  {
   "lat": 33.352445,
   "lon": -111.812562,
   "date": "2026-06-08",
   "weight": 25.0
  },
  {
   "lat": 35.357736,
   "lon": -111.771155,
   "date": "2026-06-08",
   "weight": 27.0
  },
  {
   "lat": 33.42744,
   "lon": -111.934004,
   "date": "2026-06-08",
   "weight": 72.0
  },
  {
   "lat": 32.704556,
   "lon": -114.656304,
   "date": "2026-06-08",
   "weight": 23.0
  },
  {
   "lat": 33.192391,
   "lon": -111.66594,
   "date": "2026-06-08",
   "weight": 4.0
  },
  {
   "lat": 34.598081,
   "lon": -112.420156,
   "date": "2026-06-08",
   "weight": 47.0
  },
  {
   "lat": 33.644893,
   "lon": -112.395034,
   "date": "2026-06-08",
   "weight": 2.0
  },
  {
   "lat": 33.433545,
   "lon": -111.8504,
   "date": "2026-06-08",
   "weight": 70.0
  },
  {
   "lat": 34.598251,
   "lon": -112.33074,
   "date": "2026-06-08",
   "weight": 2.0
  },
  {
   "lat": 33.317828,
   "lon": -111.830541,
   "date": "2026-06-08",
   "weight": 31.0
  },
  {
   "lat": 35.189512,
   "lon": -111.654712,
   "date": "2026-06-08",
   "weight": 3.0
  },
  {
   "lat": 32.231069,
   "lon": -110.949568,
   "date": "2026-06-08",
   "weight": 21.0
  },
  {
   "lat": 32.217037,
   "lon": -110.971338,
   "date": "2026-06-08",
   "weight": 233.0
  },
  {
   "lat": 34.878547,
   "lon": -111.858031,
   "date": "2026-06-08",
   "weight": 20.0
  },
  {
   "lat": 33.45052,
   "lon": -112.078343,
   "date": "2026-06-08",
   "weight": 413.0
  },
  {
   "lat": 33.494489,
   "lon": -111.920714,
   "date": "2026-06-08",
   "weight": 115.0
  },
  {
   "lat": 33.192391,
   "lon": -111.66594,
   "date": "2026-06-09",
   "weight": 2.0
  },
  {
   "lat": 35.189512,
   "lon": -111.654712,
   "date": "2026-06-09",
   "weight": 1.0
  },
  {
   "lat": 32.231069,
   "lon": -110.949568,
   "date": "2026-06-09",
   "weight": 22.0
  },
  {
   "lat": 33.352445,
   "lon": -111.812562,
   "date": "2026-06-09",
   "weight": 15.0
  },
  {
   "lat": 35.357736,
   "lon": -111.771155,
   "date": "2026-06-09",
   "weight": 32.0
  },
  {
   "lat": 33.42744,
   "lon": -111.934004,
   "date": "2026-06-09",
   "weight": 80.0
  },
  {
   "lat": 32.704556,
   "lon": -114.656304,
   "date": "2026-06-09",
   "weight": 26.0
  },
  {
   "lat": 33.317828,
   "lon": -111.830541,
   "date": "2026-06-09",
   "weight": 73.0
  },
  {
   "lat": 34.878547,
   "lon": -111.858031,
   "date": "2026-06-09",
   "weight": 10.0
  },
  {
   "lat": 33.45052,
   "lon": -112.078343,
   "date": "2026-06-09",
   "weight": 599.0
  },
  {
   "lat": 33.644893,
   "lon": -112.395034,
   "date": "2026-06-09",
   "weight": 14.0
  },
  {
   "lat": 34.598081,
   "lon": -112.420156,
   "date": "2026-06-09",
   "weight": 23.0
  },
  {
   "lat": 33.433545,
   "lon": -111.8504,
   "date": "2026-06-09",
   "weight": 49.0
  },
  {
   "lat": 34.598251,
   "lon": -112.33074,
   "date": "2026-06-09",
   "weight": 1.0
  },
  {
   "lat": 33.494489,
   "lon": -111.920714,
   "date": "2026-06-09",
   "weight": 50.0
  },
  {
   "lat": 32.217037,
   "lon": -110.971338,
   "date": "2026-06-09",
   "weight": 341.0
  },
  {
   "lat": 33.192391,
   "lon": -111.66594,
   "date": "2026-06-10",
   "weight": 11.0
  },
  {
   "lat": 35.189512,
   "lon": -111.654712,
   "date": "2026-06-10",
   "weight": 10.0
  },
  {
   "lat": 32.231069,
   "lon": -110.949568,
   "date": "2026-06-10",
   "weight": 19.0
  },
  {
   "lat": 33.352445,
   "lon": -111.812562,
   "date": "2026-06-10",
   "weight": 1.0
  },
  {
   "lat": 35.357736,
   "lon": -111.771155,
   "date": "2026-06-10",
   "weight": 24.0
  },
  {
   "lat": 33.42744,
   "lon": -111.934004,
   "date": "2026-06-10",
   "weight": 68.0
  },
  {
   "lat": 32.704556,
   "lon": -114.656304,
   "date": "2026-06-10",
   "weight": 45.0
  },
  {
   "lat": 33.317828,
   "lon": -111.830541,
   "date": "2026-06-10",
   "weight": 21.0
  },
  {
   "lat": 32.217037,
   "lon": -110.971338,
   "date": "2026-06-10",
   "weight": 482.0
  },
  {
   "lat": 34.878547,
   "lon": -111.858031,
   "date": "2026-06-10",
   "weight": 13.0
  },
  {
   "lat": 33.45052,
   "lon": -112.078343,
   "date": "2026-06-10",
   "weight": 1117.0
  },
  {
   "lat": 33.644893,
   "lon": -112.395034,
   "date": "2026-06-10",
   "weight": 2.0
  },
  {
   "lat": 34.598081,
   "lon": -112.420156,
   "date": "2026-06-10",
   "weight": 10.0
  },
  {
   "lat": 33.433545,
   "lon": -111.8504,
   "date": "2026-06-10",
   "weight": 79.0
  },
  {
   "lat": 33.494489,
   "lon": -111.920714,
   "date": "2026-06-10",
   "weight": 76.0
  },
  {
   "lat": 33.352445,
   "lon": -111.812562,
   "date": "2026-06-11",
   "weight": 15.0
  },
  {
   "lat": 35.357736,
   "lon": -111.771155,
   "date": "2026-06-11",
   "weight": 9.0
  },
  {
   "lat": 33.42744,
   "lon": -111.934004,
   "date": "2026-06-11",
   "weight": 77.0
  },
  {
   "lat": 32.704556,
   "lon": -114.656304,
   "date": "2026-06-11",
   "weight": 39.0
  },
  {
   "lat": 33.192391,
   "lon": -111.66594,
   "date": "2026-06-11",
   "weight": 3.0
  },
  {
   "lat": 35.189512,
   "lon": -111.654712,
   "date": "2026-06-11",
   "weight": 15.0
  },
  {
   "lat": 32.231069,
   "lon": -110.949568,
   "date": "2026-06-11",
   "weight": 22.0
  },
  {
   "lat": 32.217037,
   "lon": -110.971338,
   "date": "2026-06-11",
   "weight": 402.0
  },
  {
   "lat": 34.878547,
   "lon": -111.858031,
   "date": "2026-06-11",
   "weight": 24.0
  },
  {
   "lat": 33.45052,
   "lon": -112.078343,
   "date": "2026-06-11",
   "weight": 966.0
  },
  {
   "lat": 33.572326,
   "lon": -112.248142,
   "date": "2026-06-11",
   "weight": 1.0
  },
  {
   "lat": 33.494489,
   "lon": -111.920714,
   "date": "2026-06-11",
   "weight": 295.0
  },
  {
   "lat": 33.317828,
   "lon": -111.830541,
   "date": "2026-06-11",
   "weight": 46.0
  },
  {
   "lat": 33.644893,
   "lon": -112.395034,
   "date": "2026-06-11",
   "weight": 18.0
  },
  {
   "lat": 34.598081,
   "lon": -112.420156,
   "date": "2026-06-11",
   "weight": 48.0
  },
  {
   "lat": 33.433545,
   "lon": -111.8504,
   "date": "2026-06-11",
   "weight": 48.0
  },
  {
   "lat": 35.357736,
   "lon": -111.771155,
   "date": "2026-06-12",
   "weight": 1.0
  },
  {
   "lat": 33.352445,
   "lon": -111.812562,
   "date": "2026-06-12",
   "weight": 1.0
  },
  {
   "lat": 33.42744,
   "lon": -111.934004,
   "date": "2026-06-12",
   "weight": 4.0
  },
  {
   "lat": 32.704556,
   "lon": -114.656304,
   "date": "2026-06-12",
   "weight": 1.0
  },
  {
   "lat": 35.189512,
   "lon": -111.654712,
   "date": "2026-06-12",
   "weight": 4.0
  },
  {
   "lat": 33.494489,
   "lon": -111.920714,
   "date": "2026-06-12",
   "weight": 39.0
  },
  {
   "lat": 32.217037,
   "lon": -110.971338,
   "date": "2026-06-12",
   "weight": 89.0
  },
  {
   "lat": 33.317828,
   "lon": -111.830541,
   "date": "2026-06-12",
   "weight": 4.0
  },
  {
   "lat": 34.878547,
   "lon": -111.858031,
   "date": "2026-06-12",
   "weight": 1.0
  },
  {
   "lat": 33.45052,
   "lon": -112.078343,
   "date": "2026-06-12",
   "weight": 96.0
  }
 ]
}